[
    {
        "response": "\"I feel like I'm constantly under a microscope, expected to be flawless in every aspect of my life.\""
    },
    {
        "response": "\"It's overwhelming trying to live up to society's impossible standards of beauty and success.\""
    },
    {
        "response": "\"I'm starting to lose sight of who I really am because I'm so focused on being perfect for everyone else.\""
    },
    {
        "response": "\"I can't keep up with the pressure to always look a certain way and achieve certain goals.\""
    },
    {
        "response": "\"I feel like I'm drowning in expectations, and I don't know how to break free from them.\""
    },
    {
        "response": "\"I'm exhausted from pretending to have it all together when inside I'm falling apart.\""
    },
    {
        "response": "\"I'm starting to question my worth and value based on how well I conform to society's idea of perfection.\""
    },
    {
        "response": "\"I'm trapped in a cycle of comparison and self-doubt, constantly wondering if I'm good enough.\""
    },
    {
        "response": "\"I'm beginning to realize that the image of perfection I'm striving for is unattainable and damaging to my mental health.\""
    },
    {
        "response": "\"I need to find a way to redefine success and beauty on my own terms, or else I fear I'll lose myself completely.\""
    }
]